fsyncer/__init__.py
fsyncer/__main__.py
fsyncer/fsyncer.py
fsyncer-1.0.2.dist-info/LICENSE.txt
fsyncer-1.0.2.dist-info/METADATA
fsyncer-1.0.2.dist-info/WHEEL
fsyncer-1.0.2.dist-info/entry_points.txt
fsyncer-1.0.2.dist-info/top_level.txt
fsyncer-1.0.2.dist-info/RECORD
