Metadata-Version: 2.1
Name: fsyncer
Version: 1.0.2
Summary: Keep your repositories up-to-date all the time.
Home-page: https://github.com/Skarlso/fsyncer
Author: Gergely Brautigam
Author-email: gergely.brautigam@gmail.com
License: LICENSE.txt
Keywords: cli,git
Platform: UNKNOWN
Classifier: Intended Audience :: Developers
Classifier: Topic :: Utilities
Classifier: License :: Public Domain
Classifier: Natural Language :: English
Classifier: Operating System :: OS Independent
Classifier: Programming Language :: Python :: 3
Classifier: Programming Language :: Python :: 3.2
Classifier: Programming Language :: Python :: 3.3
Classifier: Programming Language :: Python :: 3.4
Classifier: Programming Language :: Python :: 3.5
Classifier: Programming Language :: Python :: 3.6
Requires-Dist: PyGithub
